wkcuber/__init__.py
wkcuber-0.13.0.dist-info/METADATA
wkcuber-0.13.0.dist-info/WHEEL
wkcuber-0.13.0.dist-info/RECORD
