Metadata-Version: 2.1
Name: wkcuber
Version: 0.13.0
Summary: Deprecated wkcuber package, use webknossos instead.
License: AGPL-3.0
Author: scalable minds
Author-email: hello@scalableminds.com
Requires-Python: >=3.8,<3.12
Classifier: License :: OSI Approved :: GNU Affero General Public License v3
Classifier: Programming Language :: Python :: 3
Classifier: Programming Language :: Python :: 3.8
Classifier: Programming Language :: Python :: 3.9
Classifier: Programming Language :: Python :: 3.10
Classifier: Programming Language :: Python :: 3.11
Requires-Dist: webknossos (==0.13.0)
